EC_MS/Calibration.py
EC_MS/Chips.py
EC_MS/Combining.py
EC_MS/Data_Importing.py
EC_MS/Datapoints.py
EC_MS/EC.py
EC_MS/Electrolytes.py
EC_MS/Integrate_Signals.py
EC_MS/MS.py
EC_MS/Molecules.py
EC_MS/Object_Files.py
EC_MS/PVMassSpec.py
EC_MS/Plotting.py
EC_MS/Potentiostat.py
EC_MS/Quantification.py
EC_MS/SPEC.py
EC_MS/Time_Response.py
EC_MS/Zilien.py
EC_MS/__init__.py
EC_MS/add_data.py
EC_MS/converters.py
EC_MS/dataset.py
EC_MS/parsing_tools.py
EC_MS/patches.py
EC_MS/spectra.py
EC_MS/Chem/MolarMasses.py
EC_MS/Chem/PhysCon.py
EC_MS/Chem/Thermochem.py
EC_MS/Chem/__init__.py
EC_MS/data/Electrolytes.txt
EC_MS/data/Mass_Transport.txt
EC_MS/data/Relative_Sensativity_Factors.txt
EC_MS/data/NIST_spectra_data/NIST_spectra_data.txt
EC_MS/data/NIST_spectra_data/Xe.jdx
EC_MS/data/NIST_spectra_data/acetic acid.jdx
EC_MS/data/chips/3iv1.txt
EC_MS/data/chips/DanChip-13-A1.txt
EC_MS/data/chips/DanChip-13-A2.txt
EC_MS/data/chips/DanChip-14-20A25.txt
EC_MS/data/chips/DanChip-14-20A31.txt
EC_MS/data/chips/MR12.txt
EC_MS/data/chips/SI-3iv1-1-C5.txt
EC_MS/data/chips/SI-3iv1-14-B4.txt
EC_MS/data/chips/SI-3iv1.txt
EC_MS/data/chips/SI-China-E3.txt
EC_MS/data/chips/SI-China1.txt
EC_MS/data/chips/SI-China2.txt
EC_MS/data/chips/microreactor.txt
EC_MS/data/molecules/Ar.txt
EC_MS/data/molecules/C2H4.txt
EC_MS/data/molecules/C2H6.txt
EC_MS/data/molecules/C3H6.txt
EC_MS/data/molecules/C3H8.txt
EC_MS/data/molecules/CH4.txt
EC_MS/data/molecules/CO.txt
EC_MS/data/molecules/CO2.txt
EC_MS/data/molecules/Cl2.txt
EC_MS/data/molecules/H2.txt
EC_MS/data/molecules/H2O.txt
EC_MS/data/molecules/He.txt
EC_MS/data/molecules/Henriksen2009.txt
EC_MS/data/molecules/N2.txt
EC_MS/data/molecules/NH3.txt
EC_MS/data/molecules/O2.txt
EC_MS/data/molecules/Xe.txt
EC_MS/data/molecules/acetaldehyde.txt
EC_MS/data/molecules/acetic acid.txt
EC_MS/data/molecules/air.txt
EC_MS/data/molecules/ethanol.txt
EC_MS/data/molecules/methanol.txt
EC_MS/data/molecules/propane.txt
EC_MS/data/molecules/propene.txt
EC_MS-0.7.5.dist-info/LICENSE.txt
EC_MS-0.7.5.dist-info/METADATA
EC_MS-0.7.5.dist-info/WHEEL
EC_MS-0.7.5.dist-info/top_level.txt
EC_MS-0.7.5.dist-info/RECORD
