Metadata-Version: 2.1
Name: EC-MS
Version: 0.7.5
Summary: Analysis tools for electrochemistry and mass spectrometry and a lot in between
Home-page: https://github.com/ScottSoren/EC_MS
Author: Soren B. Scott
Author-email: sbs@spectroinlets.com
Maintainer: Soren B. Scott
Maintainer-email: sbs@spectroinlets.com
License: MIT
Keywords: electrochemistry,mass spectrometry
Platform: UNKNOWN
Classifier: License :: Free for non-commercial use
Classifier: Development Status :: 3 - Alpha
Classifier: Intended Audience :: Science/Research
Classifier: Natural Language :: English
